funapi/__init__.py
funweb-0.0.1.dist-info/LICENSE
funweb-0.0.1.dist-info/METADATA
funweb-0.0.1.dist-info/WHEEL
funweb-0.0.1.dist-info/entry_points.txt
funweb-0.0.1.dist-info/top_level.txt
funweb-0.0.1.dist-info/RECORD
