Metadata-Version: 2.1
Name: funweb
Version: 0.0.1
Summary: funweb
Home-page: https://github.com/farfarfun/funweb
Author: bingtao
Author-email: 1007530194@qq.com
License-File: LICENSE
Requires-Dist: funpypi
Requires-Dist: funfile
Requires-Dist: requests
Requires-Dist: tqdm
